proxy/__init__.py
proxy/cache.py
proxy/run.py
proxy/test_cache.py
proxy/wsgi.py
pip_s3_proxy-0.2.dist-info/LICENSE
pip_s3_proxy-0.2.dist-info/METADATA
pip_s3_proxy-0.2.dist-info/WHEEL
pip_s3_proxy-0.2.dist-info/entry_points.txt
pip_s3_proxy-0.2.dist-info/top_level.txt
pip_s3_proxy-0.2.dist-info/RECORD
